cli/__init__.py
cli/api_client.py
cli/auth.py
cli/config_manager.py
cli/context_resolver.py
cli/default_config.json
cli/errors.py
cli/gh_integration.py
cli/git_commit.py
cli/git_context.py
cli/git_tag.py
cli/github_client.py
cli/github_operations.py
cli/main.py
cli/tasks.py
smooth/__init__.py
smooth/__main__.py
smooth/cli.py
smooth/commands/__init__.py
smooth/commands/auth.py
smooth/commands/commit.py
smooth/commands/config.py
smooth/commands/docs.py
smooth/commands/feedback.py
smooth/commands/pr.py
smooth/commands/pr_create.py
smooth/commands/release.py
smooth/plugin_loader.py
smooth_cli-0.3.3.dist-info/METADATA
smooth_cli-0.3.3.dist-info/WHEEL
smooth_cli-0.3.3.dist-info/entry_points.txt
smooth_cli-0.3.3.dist-info/RECORD
