Metadata-Version: 2.1
Name: smooth-cli
Version: 0.3.3
Summary: CLI utility for SD README Documentation Generator
Author: SmoothDev
Author-email: info@smoothdev.io
Requires-Python: >=3.12,<4.0
Classifier: Programming Language :: Python :: 3
Classifier: Programming Language :: Python :: 3.12
Requires-Dist: click (==8.1.7)
Requires-Dist: dulwich (>=0.21.7,<0.22.0)
Requires-Dist: gitpython (>=3.1.40,<4.0.0)
Requires-Dist: pydantic (>=2.6.0,<3.0.0)
Requires-Dist: requests (>=2.31.0,<3.0.0)
Requires-Dist: typer (>=0.12.5,<0.13.0)
